{
  "strategy_id": "strat_01jymzqv0ee05bd7w38kpzw3f7",
  "strategy_name": "V 3.0 | \u2622\ufe0f Beta Baller + TCCC \ud83d\udc8a | Deez, BrianE, HinnomTX, DereckN, Garen, DJKeyhole \ud83e\uddd9\u200d\u2642\ufe0f | AR: 9335.3%, DD 32.3% - BT date 1DEC19",
  "strategy_description": "Tactical Combat Casulty Care | If you take out the half and half last section from the v1.21 and go full YOLO with the SMH for the long term to keep the bot all semiconductor focused. Drawdown increased but massive gains increase as well. V2.1 tune up by HinnomTX (2201% to 4615% from 12/2019)",
  "version_id": "strat_01jymzqv0ee05bd7w38kpzw3f7_v1",
  "version": 1,
  "cumulative_return": 2458941.650142,
  "annualized_return": 1302.99914089683,
  "sharpe_ratio": 3.26331573356115,
  "beta": 0.6415,
  "max_drawdown": 49.142862832882,
  "backtest_start_date": "1990-01-01",
  "backtest_end_date": "2025-06-26",
  "created_at": "2025-06-26T02:05:49.094699+00:00",
  "plain_english_summary": "# Strategy: V 3.0 | \u2622\ufe0f Beta Baller + TCCC \ud83d\udc8a | Deez, BrianE, HinnomTX, DereckN, Garen, DJKeyhole \ud83e\uddd9\u200d\u2642\ufe0f | AR: 9335.3%, DD 32.3% - BT date 1DEC19\nSource: https://app.composer.trade/symphony/CGNGBrEjjJlOLFTyaEAa/details\n\n**Complexity**: High (9/10)\n**Description**: Tactical Combat Casulty Care | If you take out the half and half last section from the v1.21 and go full YOLO with the SMH for the long term to keep the bot all semiconductor focused. Drawdown increased but massive gains increase as well. V2.1 tune up by HinnomTX (2201% to 4615% from 12/2019)\n**Category**: Tactical\n\n## Trading Universe\nThis strategy can trade 39 assets:\n\n\u2022 **Stocks**: BIL, IEF, SPY, UVXY, VIXY, SOXL, SHY, HIBL, SOXS, SQQQ, TECL, TQQQ, SPXL, UPRO, QLD, TLT, SPXU, EUO, YCS, CURE, TMV, TECS, ERX, EWZ, MVV, USD, DBC, UUP, TMF, UCO, GLD, SPXS, EPI, IYK, EFA, EEM, AGG, PUI, UGE\n\n## Strategy Settings\n\u2022 **Rebalancing**: Daily\n\u2022 **Initial Capital**: USD 100,000\n\u2022 **Trading Fees**: 0.10% per trade\n\n## Investment Logic\n\n```\n\u2022 Equal Weight Allocation:\n  \u25e6 V 3.0 | \u2622\ufe0f Beta Baller + TCCC \ud83d\udc8a | Deez, BrianE, HinnomTX, DereckN, Garen, DJKeyhole \ud83e\uddd9\u200d\u2642\ufe0f | AR: 9335.3%, DD 32.3% - BT date 1DEC19:\n    \u25aa Equal Weight Allocation:\n      - If :\n        - If BIL's RSI (Relative Strength Index) (7-day) is less than IEF's RSI (Relative Strength Index) (7-day):\n          - Equal Weight Allocation:\n            - If :\n              - If SPY's RSI (Relative Strength Index) (6-day) is greater than 75.0:\n                - Overbought S&P. Sell the rip. Buy volatility.:\n                  - Equal Weight Allocation:\n                    - Select the bottom 1 asset by RSI (Relative Strength Index) (13-day) from: UVXY, VIXY\n              - Else branch:\n                - Equal Weight Allocation:\n                  - Buy SOXL (100% of portfolio)\n        - Else branch:\n          - Equal Weight Allocation:\n            - If :\n              - If SPY's RSI (Relative Strength Index) (6-day) is less than 27.0:\n                - Extremely oversold S&P (low RSI). Double check with bond mkt before going long:\n                  - Equal Weight Allocation:\n                    - If :\n                      - If SHY's RSI (Relative Strength Index) (10-day) is less than HIBL's RSI (Relative Strength Index) (10-day):\n                        - Equal Weight Allocation:\n                          - Select the bottom 1 asset by RSI (Relative Strength Index) (7-day) from: SOXS, SQQQ\n                      - Else branch:\n                        - Equal Weight Allocation:\n                          - Select the bottom 1 asset by RSI (Relative Strength Index) (7-day) from: SOXL, TECL\n              - Else branch:\n                - V0.1 | TCCC Stop the Bleed \ud83d\udc8a | DJKeyhole \ud83e\uddd9\u200d\u2642\ufe0f | 1/2 of Momentum Mean Reversion:\n                  - Equal Weight Allocation:\n                    - If :\n                      - If SPY's RSI (Relative Strength Index) (10-day) is less than 30.0:\n                        - V1.2 | Five and Below | DJKeyhole | No Low Volume LETFs:\n                          - Equal Weight Allocation:\n                            - Select the bottom 1 asset by returns (5-day) from: TECL, TQQQ, SPXL, SOXL, UPRO, QLD\n                      - Else branch:\n                        - Equal Weight Allocation:\n                          - If :\n                            - If UVXY's RSI (Relative Strength Index) (10-day) is greater than 74.0:\n                              - Equal Weight Allocation:\n                                - If :\n                                  - If UVXY's RSI (Relative Strength Index) (10-day) is greater than 84.0:\n                                    - Bear Stock Market - High Inflation - [STRIPPED] V2.0.1 | A Better LETF Basket | DJKeyhole \ud83e\uddd9\u200d\u2642\ufe0f | No UGE:\n                                      - Equal Weight Allocation:\n                                        - If :\n                                          - If TLT's current-price is greater than TLT's moving-average-price (200-day):\n                                            - A.B: Medium term TLT may be overbought*:\n                                              - Equal Weight Allocation:\n                                                - If :\n                                                  - If TLT's returns (20-day) is less than 0:\n                                                    - A.B.B.A: Risk Off, Rising Rates (TMV)*:\n                                                      - Equal Weight Allocation:\n                                                        - If :\n                                                          - If SPY's exponential-moving-average-price (210-day) is less than or equal to SPY's moving-average-price (360-day):\n                                                            - Equal Weight Allocation:\n                                                              - If :\n                                                                - If TQQQ's RSI (Relative Strength Index) (10-day) is less than 30.0:\n                                                                  - Equal Weight Allocation:\n                                                                    - Select the bottom 1 asset by returns (5-day) from: TECL, TQQQ, SOXL, UPRO\n                                                                - Else branch:\n                                                                  - Equal Weight Allocation:\n                                                                    - If :\n                                                                      - If SPXU's cumulative-return (6-day) is greater than or equal to UPRO's cumulative-return (3-day):\n                                                                        - Equal Weight Allocation:\n                                                                          - Select the top 1 asset by cumulative-return (5-day) from: SQQQ, EUO, YCS\n                                                                      - Else branch:\n                                                                        - Equal Weight Allocation:\n                                                                          - Select the bottom 1 asset by returns (5-day) from: TECL, TQQQ, SOXL, CURE\n                                                          - Else branch:\n                                                            - Equal Weight Allocation:\n                                                              - If :\n                                                                - If TQQQ's RSI (Relative Strength Index) (11-day) is greater than 77.0:\n                                                                  - Buy UVXY (100% of portfolio)\n                                                                - Else branch:\n                                                                  - Equal Weight Allocation:\n                                                                    - Select the bottom 1 asset by returns (5-day) from: TECL, TQQQ, SOXL, UPRO, TMV\n                                                  - Else branch:\n                                                    - A.B.B.B: Risk Off, Falling Rates (TMF)*:\n                                                      - Equal Weight Allocation:\n                                                        - If :\n                                                          - If SPY's exponential-moving-average-price (210-day) is less than or equal to SPY's moving-average-price (360-day):\n                                                            - Equal Weight Allocation:\n                                                              - If :\n                                                                - If TQQQ's RSI (Relative Strength Index) (10-day) is less than 30.0:\n                                                                  - Equal Weight Allocation:\n                                                                    - Select the bottom 1 asset by returns (5-day) from: TECL, TQQQ, SOXL\n                                                                - Else branch:\n                                                                  - Equal Weight Allocation:\n                                                                    - If :\n                                                                      - If SPY's cumulative-return (2-day) is less than or equal to -2.0:\n                                                                        - Equal Weight Allocation:\n                                                                          - Select the top 1 asset by cumulative-return (5-day) from: TECS, SOXS, SQQQ\n                                                                      - Else branch:\n                                                                        - Equal Weight Allocation:\n                                                                          - If :\n                                                                            - If SPXU's cumulative-return (6-day) is greater than or equal to UPRO's cumulative-return (3-day):\n                                                                              - Equal Weight Allocation:\n                                                                                - Select the top 1 asset by cumulative-return (5-day) from: ERX, EUO, YCS\n                                                                            - Else branch:\n                                                                              - Equal Weight Allocation:\n                                                                                - Select the bottom 1 asset by returns (5-day) from: SOXL, EWZ, MVV, USD\n                                                          - Else branch:\n                                                            - Equal Weight Allocation:\n                                                              - If :\n                                                                - If SPY's returns (210-day) is greater than DBC's returns (360-day):\n                                                                  - Equal Weight Allocation:\n                                                                    - If :\n                                                                      - If TQQQ's RSI (Relative Strength Index) (11-day) is greater than 77.0:\n                                                                        - Buy UVXY (100% of portfolio)\n                                                                      - Else branch:\n                                                                        - Equal Weight Allocation:\n                                                                          - If :\n                                                                            - If TQQQ's cumulative-return (6-day) is less than -10.0:\n                                                                              - Equal Weight Allocation:\n                                                                                - If :\n                                                                                  - If TQQQ's cumulative-return (1-day) is greater than 5.5:\n                                                                                    - Equal Weight Allocation:\n                                                                                      - Buy UVXY (100% of portfolio)\n                                                                                  - Else branch:\n                                                                                    - Equal Weight Allocation:\n                                                                                      - If :\n                                                                                        - If BIL's RSI (Relative Strength Index) (7-day) is less than IEF's RSI (Relative Strength Index) (7-day):\n                                                                                          - Equal Weight Allocation:\n                                                                                            - Select the bottom 1 asset by returns (5-day) from: SOXL\n                                                                                        - Else branch:\n                                                                                          - Equal Weight Allocation:\n                                                                                            - Select the top 1 asset by cumulative-return (5-day) from: EWZ, UUP, TMF, UCO\n                                                                            - Else branch:\n                                                                              - Equal Weight Allocation:\n                                                                                - If :\n                                                                                  - If BIL's RSI (Relative Strength Index) (7-day) is less than IEF's RSI (Relative Strength Index) (7-day):\n                                                                                    - Equal Weight Allocation:\n                                                                                      - Select the bottom 1 asset by returns (5-day) from: TECL, TQQQ, SPXL, QLD, USD\n                                                                                  - Else branch:\n                                                                                    - Equal Weight Allocation:\n                                                                                      - Select the top 1 asset by cumulative-return (5-day) from: EWZ, UUP, TMF\n                                                                - Else branch:\n                                                                  - Defense | Modified:\n                                                                    - Equal Weight Allocation:\n                                                                      - If :\n                                                                        - If DBC's standard-deviation-return (20-day) is greater than SPY's standard-deviation-return (20-day):\n                                                                          - Equal Weight Allocation:\n                                                                            - Select the bottom 1 asset by RSI (Relative Strength Index) (5-day) from: SHY, EWZ, GLD, SPXS, TECS, SOXS, UCO, YCS\n                                                                        - Else branch:\n                                                                          - Equal Weight Allocation:\n                                                                            - If :\n                                                                              - If BIL's RSI (Relative Strength Index) (7-day) is less than IEF's RSI (Relative Strength Index) (7-day):\n                                                                                - Equal Weight Allocation:\n                                                                                  - Select the bottom 1 asset by returns (5-day) from: SOXL, USD, TMF\n                                                                              - Else branch:\n                                                                                - Equal Weight Allocation:\n                                                                                  - Select the top 1 asset by cumulative-return (5-day) from: EWZ, SPXS, SOXS, UCO, YCS\n                                          - Else branch:\n                                            - B: If long term TLT is trending down, safety: Long Term, 2 Least Volatile*:\n                                              - Equal Weight Allocation:\n                                                - If :\n                                                  - If TLT's returns (20-day) is less than 0:\n                                                    - B.A.A: Risk Off, Rising Rates (TMV)* - LETF Basket:\n                                                      - Equal Weight Allocation:\n                                                        - If :\n                                                          - If SPY's exponential-moving-average-price (210-day) is less than or equal to SPY's moving-average-price (360-day):\n                                                            - Equal Weight Allocation:\n                                                              - If :\n                                                                - If TQQQ's RSI (Relative Strength Index) (10-day) is less than 30.0:\n                                                                  - Equal Weight Allocation:\n                                                                    - Select the top 1 asset by returns (5-day) from: TQQQ, SOXL, UPRO\n                                                                - Else branch:\n                                                                  - Equal Weight Allocation:\n                                                                    - If :\n                                                                      - If SPY's cumulative-return (2-day) is less than or equal to -2.0:\n                                                                        - Equal Weight Allocation:\n                                                                          - Select the bottom 1 asset by cumulative-return (5-day) from: SPXS, TECS, SOXS, SQQQ, ERX\n                                                                      - Else branch:\n                                                                        - Equal Weight Allocation:\n                                                                          - If :\n                                                                            - If SPXU's cumulative-return (6-day) is greater than or equal to UPRO's cumulative-return (3-day):\n                                                                              - Equal Weight Allocation:\n                                                                                - Select the top 1 asset by cumulative-return (5-day) from: SOXS, SQQQ, EPI\n                                                                            - Else branch:\n                                                                              - Equal Weight Allocation:\n                                                                                - Select the bottom 1 asset by returns (5-day) from: TECL, SOXL, TMV\n                                                          - Else branch:\n                                                            - Equal Weight Allocation:\n                                                              - If :\n                                                                - If SPY's returns (210-day) is greater than DBC's returns (360-day):\n                                                                  - Equal Weight Allocation:\n                                                                    - If :\n                                                                      - If TQQQ's RSI (Relative Strength Index) (11-day) is greater than 77.0:\n                                                                        - Buy UVXY (100% of portfolio)\n                                                                      - Else branch:\n                                                                        - Equal Weight Allocation:\n                                                                          - If :\n                                                                            - If TQQQ's cumulative-return (6-day) is less than -10.0:\n                                                                              - Equal Weight Allocation:\n                                                                                - If :\n                                                                                  - If TQQQ's cumulative-return (1-day) is greater than 5.5:\n                                                                                    - Equal Weight Allocation:\n                                                                                      - Buy UVXY (100% of portfolio)\n                                                                                  - Else branch:\n                                                                                    - Equal Weight Allocation:\n                                                                                      - Select the bottom 1 asset by returns (5-day) from: SOXL, IYK, TMV\n                                                                            - Else branch:\n                                                                              - Equal Weight Allocation:\n                                                                                - If :\n                                                                                  - If BIL's RSI (Relative Strength Index) (7-day) is less than IEF's RSI (Relative Strength Index) (7-day):\n                                                                                    - Equal Weight Allocation:\n                                                                                      - Select the top 1 asset by returns (5-day) from: TQQQ, SOXL, UPRO, TMV, IYK, TECL\n                                                                                  - Else branch:\n                                                                                    - Equal Weight Allocation:\n                                                                                      - Select the bottom 1 asset by returns (22-day) from: SOXL, UPRO, IYK\n                                                                - Else branch:\n                                                                  - Defense | Modified:\n                                                                    - Equal Weight Allocation:\n                                                                      - If :\n                                                                        - If DBC's standard-deviation-return (20-day) is greater than SPY's standard-deviation-return (20-day):\n                                                                          - Equal Weight Allocation:\n                                                                            - If :\n                                                                              - If DBC's standard-deviation-return (10-day) is greater than or equal to 3.0:\n                                                                                - Equal Weight Allocation:\n                                                                                  - If :\n                                                                                    - If TMV's standard-deviation-return (5-day) is less than or equal to DBC's standard-deviation-return (5-day):\n                                                                                      - Buy TMV (100% of portfolio)\n                                                                                    - Else branch:\n                                                                                      - Buy DBC (100% of portfolio)\n                                                                              - Else branch:\n                                                                                - Equal Weight Allocation:\n                                                                                  - If :\n                                                                                    - If BIL's RSI (Relative Strength Index) (7-day) is less than IEF's RSI (Relative Strength Index) (7-day):\n                                                                                      - Equal Weight Allocation:\n                                                                                        - Select the top 1 asset by returns (5-day) from: TMV, SOXS, SPXU\n                                                                                    - Else branch:\n                                                                                      - Equal Weight Allocation:\n                                                                                        - Select the bottom 1 asset by cumulative-return (5-day) from: EFA, EEM, SPXS, SOXS, UCO, TMV\n                                                                        - Else branch:\n                                                                          - Equal Weight Allocation:\n                                                                            - If :\n                                                                              - If BIL's RSI (Relative Strength Index) (7-day) is less than IEF's RSI (Relative Strength Index) (7-day):\n                                                                                - Equal Weight Allocation:\n                                                                                  - Select the bottom 1 asset by returns (5-day) from: EPI, SOXL, UPRO, IYK\n                                                                              - Else branch:\n                                                                                - Equal Weight Allocation:\n                                                                                  - Select the top 1 asset by cumulative-return (5-day) from: EWZ, TECS, SOXS, EUO, YCS, TMV\n                                                  - Else branch:\n                                                    - B.A.B: Risk Off, Falling Rates (TMF)* - LETF Basket:\n                                                      - Equal Weight Allocation:\n                                                        - If :\n                                                          - If SPY's exponential-moving-average-price (210-day) is less than or equal to SPY's moving-average-price (360-day):\n                                                            - Equal Weight Allocation:\n                                                              - If :\n                                                                - If SPY's cumulative-return (2-day) is less than or equal to -2.0:\n                                                                  - Equal Weight Allocation:\n                                                                    - Select the top 1 asset by cumulative-return (5-day) from: SPXS, TECS, SOXS, SQQQ\n                                                                - Else branch:\n                                                                  - Equal Weight Allocation:\n                                                                    - If :\n                                                                      - If SPXU's cumulative-return (6-day) is greater than or equal to UPRO's cumulative-return (3-day):\n                                                                        - Equal Weight Allocation:\n                                                                          - Select the bottom 1 asset by cumulative-return (5-day) from: BIL, AGG, TMF\n                                                                      - Else branch:\n                                                                        - Equal Weight Allocation:\n                                                                          - Select the bottom 1 asset by returns (5-day) from: TECL, TQQQ, SOXL, EWZ, TMF\n                                                          - Else branch:\n                                                            - Equal Weight Allocation:\n                                                              - If :\n                                                                - If SPY's returns (210-day) is greater than DBC's returns (360-day):\n                                                                  - Equal Weight Allocation:\n                                                                    - If :\n                                                                      - If SPY's exponential-moving-average-price (210-day) is greater than SPY's exponential-moving-average-price (360-day):\n                                                                        - Equal Weight Allocation:\n                                                                          - If :\n                                                                            - If TQQQ's RSI (Relative Strength Index) (11-day) is greater than 77.0:\n                                                                              - Buy UVXY (100% of portfolio)\n                                                                            - Else branch:\n                                                                              - Equal Weight Allocation:\n                                                                                - If :\n                                                                                  - If TQQQ's cumulative-return (6-day) is less than -10.0:\n                                                                                    - Equal Weight Allocation:\n                                                                                      - If :\n                                                                                        - If TQQQ's cumulative-return (1-day) is greater than 5.5:\n                                                                                          - Equal Weight Allocation:\n                                                                                            - Buy UVXY (100% of portfolio)\n                                                                                        - Else branch:\n                                                                                          - Equal Weight Allocation:\n                                                                                            - Select the bottom 1 asset by returns (7-day)\n                                                                                  - Else branch:\n                                                                                    - Equal Weight Allocation:\n                                                                                      - If :\n                                                                                        - If BIL's RSI (Relative Strength Index) (7-day) is less than IEF's RSI (Relative Strength Index) (7-day):\n                                                                                          - Equal Weight Allocation:\n                                                                                            - Select the bottom 1 asset by returns (7-day) from: TECL, SPXL, EPI, SOXL, UPRO, MVV, UGE\n                                                                                        - Else branch:\n                                                                                          - Equal Weight Allocation:\n                                                                                            - Select the top 1 asset by cumulative-return (5-day) from: SOXS, TMF\n                                                                      - Else branch:\n                                                                        - Equal Weight Allocation:\n                                                                          - Select the bottom 1 asset by RSI (Relative Strength Index) (5-day) from: SPXS, SQQQ, TECS, SOXS\n                                                                - Else branch:\n                                                                  - Defense | Modified:\n                                                                    - Equal Weight Allocation:\n                                                                      - If :\n                                                                        - If DBC's standard-deviation-return (20-day) is greater than SPY's standard-deviation-return (20-day):\n                                                                          - Equal Weight Allocation:\n                                                                            - Select the bottom 1 asset by RSI (Relative Strength Index) (5-day) from: SPXS, EPI, TECS, SOXS, SQQQ\n                                                                        - Else branch:\n                                                                          - Equal Weight Allocation:\n                                                                            - Select the top 1 asset by returns (5-day) from: TECL, TQQQ, SOXL, TMF\n                                  - Else branch:\n                                    - Buy UVXY (100% of portfolio)\n                            - Else branch:\n                              - Bear Stock Market - High Inflation - [STRIPPED] V2.0.1 | A Better LETF Basket | DJKeyhole \ud83e\uddd9\u200d\u2642\ufe0f | No UGE:\n                                - Equal Weight Allocation:\n                                  - If :\n                                    - If TLT's current-price is greater than TLT's moving-average-price (200-day):\n                                      - A.B: Medium term TLT may be overbought*:\n                                        - Equal Weight Allocation:\n                                          - If :\n                                            - If TLT's returns (20-day) is less than 0:\n                                              - A.B.B.A: Risk Off, Rising Rates (TMV)*:\n                                                - Equal Weight Allocation:\n                                                  - If :\n                                                    - If SPY's exponential-moving-average-price (210-day) is less than or equal to SPY's moving-average-price (360-day):\n                                                      - Equal Weight Allocation:\n                                                        - If :\n                                                          - If TQQQ's RSI (Relative Strength Index) (10-day) is less than 30.0:\n                                                            - Equal Weight Allocation:\n                                                              - Select the bottom 1 asset by returns (5-day) from: TECL, TQQQ, SOXL, UPRO\n                                                          - Else branch:\n                                                            - Equal Weight Allocation:\n                                                              - If :\n                                                                - If SPXU's cumulative-return (6-day) is greater than or equal to UPRO's cumulative-return (3-day):\n                                                                  - Equal Weight Allocation:\n                                                                    - Select the top 1 asset by cumulative-return (5-day) from: SQQQ, EUO, YCS\n                                                                - Else branch:\n                                                                  - Equal Weight Allocation:\n                                                                    - Select the bottom 1 asset by returns (5-day) from: TECL, TQQQ, SOXL, CURE\n                                                    - Else branch:\n                                                      - Equal Weight Allocation:\n                                                        - If :\n                                                          - If TQQQ's RSI (Relative Strength Index) (11-day) is greater than 77.0:\n                                                            - Buy UVXY (100% of portfolio)\n                                                          - Else branch:\n                                                            - Equal Weight Allocation:\n                                                              - Select the bottom 1 asset by returns (5-day) from: TECL, TQQQ, SOXL, UPRO, TMV\n                                            - Else branch:\n                                              - A.B.B.B: Risk Off, Falling Rates (TMF)*:\n                                                - Equal Weight Allocation:\n                                                  - If :\n                                                    - If SPY's exponential-moving-average-price (210-day) is less than or equal to SPY's moving-average-price (360-day):\n                                                      - Equal Weight Allocation:\n                                                        - If :\n                                                          - If TQQQ's RSI (Relative Strength Index) (10-day) is less than 30.0:\n                                                            - Equal Weight Allocation:\n                                                              - Select the bottom 1 asset by returns (5-day) from: TECL, TQQQ, SOXL\n                                                          - Else branch:\n                                                            - Equal Weight Allocation:\n                                                              - If :\n                                                                - If SPY's cumulative-return (2-day) is less than or equal to -2.0:\n                                                                  - Equal Weight Allocation:\n                                                                    - Select the top 1 asset by cumulative-return (5-day) from: TECS, SOXS, SQQQ\n                                                                - Else branch:\n                                                                  - Equal Weight Allocation:\n                                                                    - If :\n                                                                      - If SPXU's cumulative-return (6-day) is greater than or equal to UPRO's cumulative-return (3-day):\n                                                                        - Equal Weight Allocation:\n                                                                          - Select the top 1 asset by cumulative-return (5-day) from: ERX, EUO, YCS\n                                                                      - Else branch:\n                                                                        - Equal Weight Allocation:\n                                                                          - Select the bottom 1 asset by returns (5-day) from: SOXL, EWZ, MVV, USD\n                                                    - Else branch:\n                                                      - Equal Weight Allocation:\n                                                        - If :\n                                                          - If SPY's returns (210-day) is greater than DBC's returns (360-day):\n                                                            - Equal Weight Allocation:\n                                                              - If :\n                                                                - If TQQQ's RSI (Relative Strength Index) (11-day) is greater than 77.0:\n                                                                  - Buy UVXY (100% of portfolio)\n                                                                - Else branch:\n                                                                  - Equal Weight Allocation:\n                                                                    - If :\n                                                                      - If TQQQ's cumulative-return (6-day) is less than -10.0:\n                                                                        - Equal Weight Allocation:\n                                                                          - If :\n                                                                            - If TQQQ's cumulative-return (1-day) is greater than 5.5:\n                                                                              - Equal Weight Allocation:\n                                                                                - Buy UVXY (100% of portfolio)\n                                                                            - Else branch:\n                                                                              - Equal Weight Allocation:\n                                                                                - If :\n                                                                                  - If BIL's RSI (Relative Strength Index) (7-day) is less than IEF's RSI (Relative Strength Index) (7-day):\n                                                                                    - Equal Weight Allocation:\n                                                                                      - Select the bottom 1 asset by returns (5-day) from: SOXL\n                                                                                  - Else branch:\n                                                                                    - Equal Weight Allocation:\n                                                                                      - Select the top 1 asset by cumulative-return (5-day) from: EWZ, UUP, TMF, UCO\n                                                                      - Else branch:\n                                                                        - Equal Weight Allocation:\n                                                                          - If :\n                                                                            - If BIL's RSI (Relative Strength Index) (7-day) is less than IEF's RSI (Relative Strength Index) (7-day):\n                                                                              - Equal Weight Allocation:\n                                                                                - Select the bottom 1 asset by returns (5-day) from: TECL, TQQQ, SPXL, QLD, USD\n                                                                            - Else branch:\n                                                                              - Equal Weight Allocation:\n                                                                                - Select the top 1 asset by cumulative-return (5-day) from: EWZ, UUP, TMF\n                                                          - Else branch:\n                                                            - Defense | Modified:\n                                                              - Equal Weight Allocation:\n                                                                - If :\n                                                                  - If DBC's standard-deviation-return (20-day) is greater than SPY's standard-deviation-return (20-day):\n                                                                    - Equal Weight Allocation:\n                                                                      - Select the bottom 1 asset by RSI (Relative Strength Index) (5-day) from: SHY, EWZ, GLD, SPXS, TECS, SOXS, UCO, YCS\n                                                                  - Else branch:\n                                                                    - Equal Weight Allocation:\n                                                                      - If :\n                                                                        - If BIL's RSI (Relative Strength Index) (7-day) is less than IEF's RSI (Relative Strength Index) (7-day):\n                                                                          - Equal Weight Allocation:\n                                                                            - Select the bottom 1 asset by returns (5-day) from: SOXL, USD, TMF\n                                                                        - Else branch:\n                                                                          - Equal Weight Allocation:\n                                                                            - Select the top 1 asset by cumulative-return (5-day) from: EWZ, SPXS, SOXS, UCO, YCS\n                                    - Else branch:\n                                      - B: If long term TLT is trending down, safety: Long Term, 2 Least Volatile*:\n                                        - Equal Weight Allocation:\n                                          - If :\n                                            - If TLT's returns (20-day) is less than 0:\n                                              - B.A.A: Risk Off, Rising Rates (TMV)* - LETF Basket:\n                                                - Equal Weight Allocation:\n                                                  - If :\n                                                    - If SPY's exponential-moving-average-price (210-day) is less than or equal to SPY's moving-average-price (360-day):\n                                                      - Equal Weight Allocation:\n                                                        - If :\n                                                          - If TQQQ's RSI (Relative Strength Index) (10-day) is less than 30.0:\n                                                            - Equal Weight Allocation:\n                                                              - Select the top 1 asset by returns (5-day) from: TQQQ, SOXL, UPRO\n                                                          - Else branch:\n                                                            - Equal Weight Allocation:\n                                                              - If :\n                                                                - If SPY's cumulative-return (2-day) is less than or equal to -2.0:\n                                                                  - Equal Weight Allocation:\n                                                                    - Select the bottom 1 asset by cumulative-return (5-day) from: SPXS, TECS, SOXS, SQQQ, ERX\n                                                                - Else branch:\n                                                                  - Equal Weight Allocation:\n                                                                    - If :\n                                                                      - If SPXU's cumulative-return (6-day) is greater than or equal to UPRO's cumulative-return (3-day):\n                                                                        - Equal Weight Allocation:\n                                                                          - Select the top 1 asset by cumulative-return (5-day) from: SOXS, SQQQ, EPI\n                                                                      - Else branch:\n                                                                        - Equal Weight Allocation:\n                                                                          - Select the bottom 1 asset by returns (5-day) from: TECL, SOXL, TMV\n                                                    - Else branch:\n                                                      - Equal Weight Allocation:\n                                                        - If :\n                                                          - If SPY's returns (210-day) is greater than DBC's returns (360-day):\n                                                            - Equal Weight Allocation:\n                                                              - If :\n                                                                - If TQQQ's RSI (Relative Strength Index) (11-day) is greater than 77.0:\n                                                                  - Buy UVXY (100% of portfolio)\n                                                                - Else branch:\n                                                                  - Equal Weight Allocation:\n                                                                    - If :\n                                                                      - If TQQQ's cumulative-return (6-day) is less than -10.0:\n                                                                        - Equal Weight Allocation:\n                                                                          - If :\n                                                                            - If TQQQ's cumulative-return (1-day) is greater than 5.5:\n                                                                              - Equal Weight Allocation:\n                                                                                - Buy UVXY (100% of portfolio)\n                                                                            - Else branch:\n                                                                              - Equal Weight Allocation:\n                                                                                - Select the bottom 1 asset by returns (5-day) from: SOXL, IYK, TMV\n                                                                      - Else branch:\n                                                                        - Equal Weight Allocation:\n                                                                          - If :\n                                                                            - If BIL's RSI (Relative Strength Index) (7-day) is less than IEF's RSI (Relative Strength Index) (7-day):\n                                                                              - Equal Weight Allocation:\n                                                                                - Select the top 1 asset by returns (5-day) from: TQQQ, SOXL, UPRO, TMV, IYK, TECL\n                                                                            - Else branch:\n                                                                              - Equal Weight Allocation:\n                                                                                - Select the bottom 1 asset by returns (22-day) from: SOXL, UPRO, IYK\n                                                          - Else branch:\n                                                            - Defense | Modified:\n                                                              - Equal Weight Allocation:\n                                                                - If :\n                                                                  - If DBC's standard-deviation-return (20-day) is greater than SPY's standard-deviation-return (20-day):\n                                                                    - Equal Weight Allocation:\n                                                                      - If :\n                                                                        - If DBC's standard-deviation-return (10-day) is greater than or equal to 3.0:\n                                                                          - Equal Weight Allocation:\n                                                                            - If :\n                                                                              - If TMV's standard-deviation-return (5-day) is less than or equal to DBC's standard-deviation-return (5-day):\n                                                                                - Buy TMV (100% of portfolio)\n                                                                              - Else branch:\n                                                                                - Buy DBC (100% of portfolio)\n                                                                        - Else branch:\n                                                                          - Equal Weight Allocation:\n                                                                            - If :\n                                                                              - If BIL's RSI (Relative Strength Index) (7-day) is less than IEF's RSI (Relative Strength Index) (7-day):\n                                                                                - Equal Weight Allocation:\n                                                                                  - Select the top 1 asset by returns (5-day) from: TMV, SOXS, SPXU\n                                                                              - Else branch:\n                                                                                - Equal Weight Allocation:\n                                                                                  - Select the bottom 1 asset by cumulative-return (5-day) from: EFA, EEM, SPXS, SOXS, UCO, TMV\n                                                                  - Else branch:\n                                                                    - Equal Weight Allocation:\n                                                                      - If :\n                                                                        - If BIL's RSI (Relative Strength Index) (7-day) is less than IEF's RSI (Relative Strength Index) (7-day):\n                                                                          - Equal Weight Allocation:\n                                                                            - Select the bottom 1 asset by returns (5-day) from: EPI, SOXL, UPRO, IYK\n                                                                        - Else branch:\n                                                                          - Equal Weight Allocation:\n                                                                            - Select the top 1 asset by cumulative-return (5-day) from: EWZ, TECS, SOXS, EUO, YCS, TMV\n                                            - Else branch:\n                                              - B.A.B: Risk Off, Falling Rates (TMF)* - LETF Basket:\n                                                - Equal Weight Allocation:\n                                                  - If :\n                                                    - If SPY's exponential-moving-average-price (210-day) is less than or equal to SPY's moving-average-price (360-day):\n                                                      - Equal Weight Allocation:\n                                                        - If :\n                                                          - If SPY's cumulative-return (2-day) is less than or equal to -2.0:\n                                                            - Equal Weight Allocation:\n                                                              - Select the top 1 asset by cumulative-return (5-day) from: SPXS, TECS, SOXS, SQQQ\n                                                          - Else branch:\n                                                            - Equal Weight Allocation:\n                                                              - If :\n                                                                - If SPXU's cumulative-return (6-day) is greater than or equal to UPRO's cumulative-return (3-day):\n                                                                  - Equal Weight Allocation:\n                                                                    - Select the bottom 1 asset by cumulative-return (5-day) from: BIL, AGG, TMF\n                                                                - Else branch:\n                                                                  - Equal Weight Allocation:\n                                                                    - Select the bottom 1 asset by returns (5-day) from: TECL, TQQQ, SOXL, EWZ, TMF\n                                                    - Else branch:\n                                                      - Equal Weight Allocation:\n                                                        - If :\n                                                          - If SPY's returns (210-day) is greater than DBC's returns (360-day):\n                                                            - Equal Weight Allocation:\n                                                              - If :\n                                                                - If SPY's exponential-moving-average-price (210-day) is greater than SPY's exponential-moving-average-price (360-day):\n                                                                  - Equal Weight Allocation:\n                                                                    - If :\n                                                                      - If TQQQ's RSI (Relative Strength Index) (11-day) is greater than 77.0:\n                                                                        - Buy UVXY (100% of portfolio)\n                                                                      - Else branch:\n                                                                        - Equal Weight Allocation:\n                                                                          - If :\n                                                                            - If TQQQ's cumulative-return (6-day) is less than -10.0:\n                                                                              - Equal Weight Allocation:\n                                                                                - If :\n                                                                                  - If TQQQ's cumulative-return (1-day) is greater than 5.5:\n                                                                                    - Equal Weight Allocation:\n                                                                                      - Buy UVXY (100% of portfolio)\n                                                                                  - Else branch:\n                                                                                    - Equal Weight Allocation:\n                                                                                      - Select the bottom 1 asset by returns (7-day)\n                                                                            - Else branch:\n                                                                              - Equal Weight Allocation:\n                                                                                - If :\n                                                                                  - If BIL's RSI (Relative Strength Index) (7-day) is less than IEF's RSI (Relative Strength Index) (7-day):\n                                                                                    - Equal Weight Allocation:\n                                                                                      - Select the bottom 1 asset by returns (7-day) from: TECL, SPXL, EPI, SOXL, UPRO, MVV, UGE\n                                                                                  - Else branch:\n                                                                                    - Equal Weight Allocation:\n                                                                                      - Select the top 1 asset by cumulative-return (5-day) from: SOXS, TMF\n                                                                - Else branch:\n                                                                  - Equal Weight Allocation:\n                                                                    - Select the bottom 1 asset by RSI (Relative Strength Index) (5-day) from: SPXS, SQQQ, TECS, SOXS\n                                                          - Else branch:\n                                                            - Defense | Modified:\n                                                              - Equal Weight Allocation:\n                                                                - If :\n                                                                  - If DBC's standard-deviation-return (20-day) is greater than SPY's standard-deviation-return (20-day):\n                                                                    - Equal Weight Allocation:\n                                                                      - Select the bottom 1 asset by RSI (Relative Strength Index) (5-day) from: SPXS, EPI, TECS, SOXS, SQQQ\n                                                                  - Else branch:\n                                                                    - Equal Weight Allocation:\n                                                                      - Select the top 1 asset by returns (5-day) from: TECL, TQQQ, SOXL, TMF\n```\n\n## Technical Details\n\u2022 **Source Platform**: Composer\n\u2022 **Source ID**: CGNGBrEjjJlOLFTyaEAa\n\u2022 **Created**: June 26, 2025\n\u2022 **Slippage Model**: 0.10% per trade\n"
}